<dados>
	<tabela = locadora>
		<registro>
			<NomeFantasiaLocadora>Teste</NomefantasiaLocadora>
			<RazaoSocialLocadora>Teste</RazaoSocialLocadora>
			<IncricaoEstadualLocadora>123456789</IncricaoEstadualLocadora>
			<CNPJLocadora>12.345.678/9012-31</CNPJLocadora>
			<EnderecoLocadora>R. Teste, 1, Teste</EnderecoLocadora>
			<TelefoneLocadora>(12)3456-7899</TelefoneLocadora>
			<EmailLocadora>teste@gmail.com</EmailLocadora>
			<MultaLocadora>1,50</MultaLocadora>
			<NomeResponsavelLocadora>Teste</NomeResponsavelLocadora>
			<TelefoneResponsavelLocadora>(12)3456-7899</TelefoneResponsavelLocadora>
			<Caixa>9732.05</Caixa>
			<TotalLocado>4</TotalLocado>
		</registro>
	</tabela>
	<tabela = cliente>
		<registro>
			<CodigoCliente>C000001</CodigoCliente>
			<NomeCliente>Cliente1</NomeCliente>
			<EnderecoCliente>Cliente1</EnderecoCliente>
			<CPFCliente>111.111.111-11</CPFCliente>
			<TelefoneCliente>(11)1111-1111</TelefoneCliente>
			<EmailCliente>cliente1@gmail.com</EmailCliente>
			<SexoCliente>Masculino</SexoCliente>
			<EstadoCivilCliente>Solteiro(a)</EstadoCivilCliente>
			<NascimentoCliente>11/11/1111</NascimentoCliente>
			<DeleteCliente>FALSE</DeleteCliente>
		</registro>
		<registro>
			<CodigoCliente>C000002</CodigoCliente>
			<NomeCliente>Cliente2</NomeCliente>
			<EnderecoCliente>Cliente2</EnderecoCliente>
			<CPFCliente>222.222.222-22</CPFCliente>
			<TelefoneCliente>(22)2222-2222</TelefoneCliente>
			<EmailCliente>cliente2@gmail.com</EmailCliente>
			<SexoCliente>Feminino</SexoCliente>
			<EstadoCivilCliente>Casado(a)</EstadoCivilCliente>
			<NascimentoCliente>22/22/2222</NascimentoCliente>
			<DeleteCliente>FALSE</DeleteCliente>
		</registro>
		<registro>
			<CodigoCliente>C000003</CodigoCliente>
			<NomeCliente>Cliente3</NomeCliente>
			<EnderecoCliente>R. Cliente 3</EnderecoCliente>
			<CPFCliente>333.333.333-33</CPFCliente>
			<TelefoneCliente>(33)3333-3333</TelefoneCliente>
			<EmailCliente>cliente3@gmail.com</EmailCliente>
			<SexoCliente>Masculino</SexoCliente>
			<EstadoCivilCliente>Divorciado(a)</EstadoCivilCliente>
			<NascimentoCliente>33/33/3333</NascimentoCliente>
			<DeleteCliente>FALSE</DeleteCliente>
		</registro>
		<registro>
			<CodigoCliente>C000004</CodigoCliente>
			<NomeCliente>Cliente4</NomeCliente>
			<EnderecoCliente>R. Cliente4</EnderecoCliente>
			<CPFCliente>444.444.444-44</CPFCliente>
			<TelefoneCliente>(44)4444-4444</TelefoneCliente>
			<EmailCliente>cliente4@gmail.com</EmailCliente>
			<SexoCliente>Feminino</SexoCliente>
			<EstadoCivilCliente>Viúvo(a)</EstadoCivilCliente>
			<NascimentoCliente>44/44/4444</NascimentoCliente>
			<DeleteCliente>FALSE</DeleteCliente>
		</registro>
	</tabela>
	<tabela = filme>
		<registro>
			<CodigoFilme>F000001</CodigoFilme>
			<DescricaoFilme>Filme1</DescricaoFilme>
			<ExemplaresFilme>99</ExemplaresFilme>
			<CodCatFilme>CAT000001</CodCatFilme>
			<LinguaFilme>Legendado</LinguaFilme>
			<PrecoFilme>0</PrecoFilme>
			<DeleteFilme>FALSE</DeleteFilme>
			<VezesFilme>1</VezesFilme>
		</registro>
		<registro>
			<CodigoFilme>F000002</CodigoFilme>
			<DescricaoFilme>Filme2</DescricaoFilme>
			<ExemplaresFilme>99</ExemplaresFilme>
			<CodCatFilme>CAT000002</CodCatFilme>
			<LinguaFilme>Dublado</LinguaFilme>
			<PrecoFilme>0</PrecoFilme>
			<DeleteFilme>FALSE</DeleteFilme>
			<VezesFilme>1</VezesFilme>
		</registro>
		<registro>
			<CodigoFilme>F000003</CodigoFilme>
			<DescricaoFilme>Filme3</DescricaoFilme>
			<ExemplaresFilme>99</ExemplaresFilme>
			<CodCatFilme>CAT000003</CodCatFilme>
			<LinguaFilme>Legendado</LinguaFilme>
			<PrecoFilme>0</PrecoFilme>
			<DeleteFilme>FALSE</DeleteFilme>
			<VezesFilme>1</VezesFilme>
		</registro>
		<registro>
			<CodigoFilme>F000004</CodigoFilme>
			<DescricaoFilme>Filme4</DescricaoFilme>
			<ExemplaresFilme>99</ExemplaresFilme>
			<CodCatFilme>CAT000004</CodCatFilme>
			<LinguaFilme>Dublado</LinguaFilme>
			<PrecoFilme>0</PrecoFilme>
			<DeleteFilme>FALSE</DeleteFilme>
			<VezesFilme>1</VezesFilme>
		</registro>
	</tabela>
	<tabela = categoria>
		<registro>
			<CodigoCategoria>CAT000001</CodigoCategoria>
			<ValorCategoria>5,00</ValorCategoria>
			<DescricaoCategoria>Categoria1</DescricaoCategoria>
			<DeleteCategoria>FALSE</DeleteCategoria>
		</registro>
		<registro>
			<CodigoCategoria>CAT000002</CodigoCategoria>
			<ValorCategoria>10,00</ValorCategoria>
			<DescricaoCategoria>Categoria2</DescricaoCategoria>
			<DeleteCategoria>FALSE</DeleteCategoria>
		</registro>
		<registro>
			<CodigoCategoria>CAT000003</CodigoCategoria>
			<ValorCategoria>15,00</ValorCategoria>
			<DescricaoCategoria>Categoria3</DescricaoCategoria>
			<DeleteCategoria>FALSE</DeleteCategoria>
		</registro>
		<registro>
			<CodigoCategoria>CAT000004</CodigoCategoria>
			<ValorCategoria>3,00</ValorCategoria>
			<DescricaoCategoria>Categoria4</DescricaoCategoria>
			<DeleteCategoria>FALSE</DeleteCategoria>
		</registro>
	</tabela>
	<tabela = funcionario>
		<registro>
			<CodigoFuncionario>FUN000001</CodigoFuncionario>
			<NomeFuncionario>Funcionário1</NomeFuncionario>
			<CargoFuncionario>Vendedor</CargoFuncionario>
			<EmailFuncionario>funcionario1@gmail.com</EmailFuncionario>
			<EnderecoFuncionario>R. Funcionário1, 1</EnderecoFuncionario>
			<TelefoneFuncionario>(11)1111-1111</TelefoneFuncionario>
			<DeleleFuncionario>FALSE</DeleleFuncionario>
			<TotalLocado>2</TotalLocado>
		</registro>
		<registro>
			<CodigoFuncionario>FUN000002</CodigoFuncionario>
			<NomeFuncionario>Funcionário2</NomeFuncionario>
			<CargoFuncionario>Gerente</CargoFuncionario>
			<EmailFuncionario>funcionario2@gmail.com</EmailFuncionario>
			<EnderecoFuncionario>R. Funcionario2, 2</EnderecoFuncionario>
			<TelefoneFuncionario>(22)2222-2222</TelefoneFuncionario>
			<DeleleFuncionario>FALSE</DeleleFuncionario>
			<TotalLocado>2</TotalLocado>
		</registro>
		<registro>
			<CodigoFuncionario>FUN000003</CodigoFuncionario>
			<NomeFuncionario>Funcionário3</NomeFuncionario>
			<CargoFuncionario>Vendedor</CargoFuncionario>
			<EmailFuncionario>funcionario3@gmail.com</EmailFuncionario>
			<EnderecoFuncionario>R. Funcionario3, 3</EnderecoFuncionario>
			<TelefoneFuncionario>(33)3333-3333</TelefoneFuncionario>
			<DeleleFuncionario>FALSE</DeleleFuncionario>
			<TotalLocado>0</TotalLocado>
		</registro>
		<registro>
			<CodigoFuncionario>FUN000004</CodigoFuncionario>
			<NomeFuncionario>Funcionário4</NomeFuncionario>
			<CargoFuncionario>Gerente</CargoFuncionario>
			<EmailFuncionario>funcionario4@gmail.com</EmailFuncionario>
			<EnderecoFuncionario>R. Funcionario4, 4</EnderecoFuncionario>
			<TelefoneFuncionario>(44)4444-4444</TelefoneFuncionario>
			<DeleleFuncionario>FALSE</DeleleFuncionario>
			<TotalLocado>0</TotalLocado>
		</registro>
	</tabela>
	<tabela = fornecedor>
		<registro>
			<CodigoFornecedor>FOR000001</CodigoFornecedor>
			<NomeFornecedor>Fornecedor1</NomeFornecedor>
			<RazaoFornecedor>Fornecedor1</RazaoFornecedor>
			<InscricaoFornecedor>12312312312</InscricaoFornecedor>
			<CNPJFornecedor>12.312.312/3123-12</CNPJFornecedor>
			<EmailFornecedor>fornecedor1@gmail.com</EmailFornecedor>
			<EnderecoFornecedor>R.Fornecedor1,1</EnderecoFornecedor>
			<TelefoneFornecedor>(11)1111-1111</TelefoneFornecedor>
			<DeleteFornecedor>FALSE</DeleteFornecedor>
		</registro>
		<registro>
			<CodigoFornecedor>FOR000002</CodigoFornecedor>
			<NomeFornecedor>Fornecedor2</NomeFornecedor>
			<RazaoFornecedor>Fornecedor2</RazaoFornecedor>
			<InscricaoFornecedor>1237162325</InscricaoFornecedor>
			<CNPJFornecedor>17.236.123/6127-36</CNPJFornecedor>
			<EmailFornecedor>fornecedor2@gmail.com</EmailFornecedor>
			<EnderecoFornecedor>R. Fornecedor2, 2</EnderecoFornecedor>
			<TelefoneFornecedor>(22)2222-2222</TelefoneFornecedor>
			<DeleteFornecedor>FALSE</DeleteFornecedor>
		</registro>
		<registro>
			<CodigoFornecedor>FOR000003</CodigoFornecedor>
			<NomeFornecedor>Fornecedor3</NomeFornecedor>
			<RazaoFornecedor>Fornecedor3</RazaoFornecedor>
			<InscricaoFornecedor>123123123123</InscricaoFornecedor>
			<CNPJFornecedor>12.481.647/1247-25</CNPJFornecedor>
			<EmailFornecedor>fornecedor3@gmail.com</EmailFornecedor>
			<EnderecoFornecedor>R. Fornecedor3, 3</EnderecoFornecedor>
			<TelefoneFornecedor>(33)3333-3333</TelefoneFornecedor>
			<DeleteFornecedor>FALSE</DeleteFornecedor>
		</registro>
		<registro>
			<CodigoFornecedor>FOR000004</CodigoFornecedor>
			<NomeFornecedor>Fornecedor4</NomeFornecedor>
			<RazaoFornecedor>Fornecedor4</RazaoFornecedor>
			<InscricaoFornecedor>1623761253</InscricaoFornecedor>
			<CNPJFornecedor>23.762.734/6237-62</CNPJFornecedor>
			<EmailFornecedor>fornecedor4@gmail.com</EmailFornecedor>
			<EnderecoFornecedor>R. Fornecedor4, 4</EnderecoFornecedor>
			<TelefoneFornecedor>(44)4444-4444</TelefoneFornecedor>
			<DeleteFornecedor>FALSE</DeleteFornecedor>
		</registro>
	</tabela>
	<tabela = contas_receber>
	</tabela>
	<tabela = devolucao>
	</tabela>
	<tabela = contas_pagar>
	</tabela>
</dados>
